<text text-id="bgu.4.1188">
  <sentence n="position in the document">
    <token p="passage-level id" n="position in @p" a="nth occurrence in @p" o="Mate tagger POS tag" u="position in s element" join="optional: join b(ack) or a(fter) for punctuation marks">
      <wordForm>word form of the token</wordForm>
      <lemma id="contains the id number of the entry in the database consisting of the set of all word forms + morphological analyses of all Greek texts">
        <l1>as many l1 elements as the lemmas found in PerseusUnderPhilologic for 
              the relevant word form AND morphological analysis</l1>
        <l2>as many l2 elements as the lemmas found in Morpheus for 
              the relevant word form AND morphological analysis</l2>
      </lemma>
    </token>
  </sentence>
  <s n="1">
    <t p="1" n="1" a="[1]" o="n-s---md-" u="1">
      <f>Ἡρακλείδηι</f>
    </t>
    <t p="1" n="2" a="[1]" o="n-p---md-" u="2">
      <f>στρατηγῶι</f>
    </t>
    <t p="1" n="3" a="[1]" o="d--------" u="3">
      <f>καὶ</f>
      <l r="d---------">καί</l>
    </t>
    <t p="1" n="4" a="[1]" o="r--------" u="4">
      <f>ἐπὶ</f>
      <l r="r---------">ἐπί</l>
      <e>ἐπί</e>
    </t>
    <t p="1" n="5" a="[1]" o="l-p---ng-" u="5">
      <f>τῶν</f>
      <e>ὁ</e>
    </t>
    <t p="1" n="6" a="[1]" o="n-p---ng-" u="6">
      <f>προσόδων</f>
    </t>
    <t p="1" n="7" a="[1]" join="b" o="u--------" u="7">
      <f>·</f>
    </t>
  </s>
  <s n="2">
    <t p="1" n="8" a="[2]" join="b" o="u--------" u="1">
      <f>·</f>
    </t>
  </s>
  <s n="3">
    <t p="2" n="1" a="[1]" o="r--------" u="1">
      <f>παρὰ</f>
      <l r="r---------">παρά</l>
    </t>
    <t p="2" n="2" a="[1]" o="n-s---mg-" u="2">
      <f>Κάστορος</f>
      <l r="ne-s---mg-">Κάστωρ</l>
    </t>
    <t p="2" n="3" a="[1]" o="a-s---mg-" u="3">
      <f>γυμνασιάρχου</f>
    </t>
    <t p="2" n="4" a="[1]" o="n-s---fn-" u="4">
      <f>Κόμα</f>
    </t>
    <t p="2" n="5" a="[1]" o="d--------" u="5">
      <f>καὶ</f>
      <l r="d---------">καί</l>
    </t>
    <t p="2" n="6" a="[1]" o="l-p---mg-" u="6">
      <f>τῶν</f>
      <e>ὁ</e>
    </t>
    <t p="3" n="1" a="[1]" o="a-p---mg-" u="7">
      <f>ἄλλων</f>
      <l r="a--p---mg-">ἄλλος</l>
      <e>ἄλλος</e>
    </t>
    <t p="3" n="2" a="[1]" o="l-p---mg-" u="8">
      <f>τῶν</f>
      <e>ὁ</e>
    </t>
    <t p="3" n="3" a="[1]" o="r--------" u="9">
      <f>ἐν</f>
      <l r="r---------">ἐν</l>
      <e>εἰς</e>
      <e>ἐν</e>
    </t>
    <t p="3" n="4" a="[1]" o="n-s---fd-" u="10">
      <f>τῆι</f>
    </t>
    <t p="3" n="5" a="[1]" o="d--------" u="11">
      <f>κώμηι</f>
    </t>
    <t p="3" n="6" a="[1]" o="n-p---mg-" u="12">
      <f>κατοίκων</f>
    </t>
    <t p="3" n="7" a="[1]" o="d--------" u="13">
      <f>καὶ</f>
      <l r="d---------">καί</l>
    </t>
    <t p="3" n="8" a="[2]" o="l-p---mg-" u="14">
      <f>τῶν</f>
      <e>ὁ</e>
    </t>
    <t p="4" n="1" a="[1]" o="a-p---mg-" u="15">
      <f>ἄλλων</f>
      <l r="a--p---mg-">ἄλλος</l>
      <e>ἄλλος</e>
    </t>
    <t p="4" n="2" a="[1]" o="n-p---mg-" u="16">
      <f>γεωργῶν</f>
    </t>
    <t p="4" n="3" a="[1]" o="d--------" u="17">
      <f>καὶ</f>
      <l r="d---------">καί</l>
    </t>
    <t p="4" n="4" a="[1]" o="l-p---mg-" u="18">
      <f>τῶν</f>
      <e>ὁ</e>
    </t>
    <t p="4" n="5" a="[1]" o="a-p---fg-" u="19">
      <f>βασιλικῶν</f>
      <l r="a--p---fg-">βασιλικός</l>
      <e>βασιλικός</e>
    </t>
    <t p="4" n="6" a="[2]" o="n-p---fg-" u="20">
      <f>γεωργῶν</f>
    </t>
    <t p="5" n="1" a="[1]" o="l-p---mg-" u="21">
      <f>τῶν</f>
      <e>ὁ</e>
    </t>
    <t p="5" n="2" a="[1]" o="r--------" u="22">
      <f>ἐν</f>
      <l r="r---------">ἐν</l>
      <e>εἰς</e>
      <e>ἐν</e>
    </t>
    <t p="5" n="3" a="[1]" o="n-s---fd-" u="23">
      <f>τῆι</f>
    </t>
    <t p="5" n="4" a="[1]" o="n-s---md-" u="24">
      <f>κώμηι</f>
    </t>
    <t p="5" n="5" a="[1]" o="v-pppamg-" u="25">
      <f>κατοικούντων</f>
      <l r="v--pppamg-">κατοικέω</l>
    </t>
    <t p="5" n="6" a="[1]" join="b" o="u--------" u="26">
      <f>.</f>
    </t>
  </s>
  <s n="4">
    <t p="5" n="7" a="[1]" o="d--------" u="1">
      <f>ἔτι</f>
      <l r="d---------">ἔτι</l>
      <e>ἔτι</e>
    </t>
    <t p="5" n="8" a="[1]" o="r--------" u="2">
      <f>ἀπὸ</f>
      <l r="r---------">ἀπό</l>
    </t>
    <t p="5" n="9" a="[1]" o="l-s---ng-" u="3">
      <f>τοῦ</f>
      <e>ὁ</e>
    </t>
    <t p="6" n="1" a="[1]" o="d--------" u="4">
      <f>ιϛ</f>
    </t>
    <t p="6" n="2" a="[1]" o="a-p---ma-" u="5">
      <f>ἔτους</f>
    </t>
    <t p="6" n="3" a="[1]" o="n-s---mg-" u="6">
      <f>Καίσαρος</f>
      <l r="ne-s---mg-">Καῖσαρ</l>
    </t>
    <t p="6" n="4" a="[1]" o="l-s---mg-" u="7">
      <f>τοῦ</f>
      <e>ὁ</e>
    </t>
    <t p="6" n="5" a="[1]" o="r--------" u="8">
      <f>κατὰ</f>
      <l r="r---------">κατά</l>
      <e>κατά</e>
    </t>
    <t p="6" n="6" a="[1]" o="l-s---fa-" u="9">
      <f>τὴν</f>
    </t>
    <t p="6" n="7" a="[1]" o="n-s---fa-" u="10">
      <f>κώμην</f>
      <l r="n--s---fa-">κώμη</l>
      <e>κώμη</e>
    </t>
    <t p="6" n="8" a="[1]" o="v-sapmmg-" u="11">
      <f>ἀγομένου</f>
    </t>
    <t p="7" n="1" a="[1]" o="a-s---mg-" u="12">
      <f>δημοσίου</f>
      <l r="a--s---mg-">δημόσιος</l>
      <e>δημόσιος</e>
    </t>
    <t p="7" n="2" a="[1]" o="n-s---ng-" u="13">
      <f>διαζώματος</f>
      <l r="n--s---ng-">διάζωμα</l>
      <e>διάζωμα</e>
    </t>
    <t p="7" n="3" a="[1]" o="v3slie---" u="14">
      <f>το</f>
    </t>
    <t p="7" n="4" a="[1]" join="b" o="u--------" u="15">
      <f>,</f>
    </t>
    <t p="7" n="5" a="[1]" o="r--------" u="16">
      <f>διὰ</f>
      <l r="r---------">διά</l>
    </t>
    <t p="7" n="6" a="[1]" o="c--------" u="17">
      <f>δὲ</f>
    </t>
    <t p="7" n="7" a="[1]" o="l-p---ma-" u="18">
      <f>τοὺς</f>
    </t>
    <t p="7" n="8" a="[1]" o="r--------" u="19">
      <f>ἐκ</f>
      <l r="r---------">ἐκ</l>
      <e>ἐκ</e>
    </t>
    <t p="7" n="9" a="[1]" o="a-s---ng-" u="20">
      <f>τούτου</f>
      <e>οὗτος</e>
    </t>
    <t p="8" n="1" a="[1]" o="v-pppema-" u="21">
      <f>γεινομένους</f>
    </t>
    <t p="8" n="2" a="[1]" o="n-p---ma-" u="22">
      <f>διακόπους</f>
    </t>
    <t p="8" n="3" a="[1]" o="v3spia---" u="23">
      <f>ὑπάρχει</f>
      <l r="v-3spia---">ὑπάρχω</l>
      <e>ὑπάρχω</e>
    </t>
    <t p="8" n="4" a="[1]" o="p1p---md-" u="24">
      <f>ἡμῖν</f>
      <e>ἐγώ</e>
    </t>
    <t p="8" n="5" a="[1]" o="r--------" u="25">
      <f>ἐν</f>
      <l r="r---------">ἐν</l>
      <e>εἰς</e>
      <e>ἐν</e>
    </t>
    <t p="8" n="6" a="[1]" o="n-s---md-" u="26">
      <f>τῆι</f>
    </t>
    <t p="9" n="1" a="[1]" o="n-s---md-" u="27">
      <f>κώμηι</f>
    </t>
    <t p="9" n="2" a="[1]" o="a-s---ma-" u="28">
      <f>πορθμεῖον</f>
    </t>
    <t p="9" n="3" a="[1]" join="b" o="u--------" u="29">
      <f>,</f>
    </t>
    <t p="9" n="4" a="[1]" o="r--------" u="30">
      <f>διʼ</f>
      <l r="r---------">διά</l>
    </t>
    <t p="9" n="5" a="[1]" o="p-s---mg-" u="31">
      <f>οὗ</f>
      <l r="pp-s---mg-">οὗ2</l>
      <l r="pr-s---mg-">ὅς</l>
      <l r="ps-s---mg-">ὅς2</l>
      <e>ἕ</e>
      <e>ὅς</e>
    </t>
    <t p="9" n="6" a="[1]" o="d--------" u="32">
      <f>καὶ</f>
      <l r="d---------">καί</l>
    </t>
    <t p="9" n="7" a="[1]" o="l-p---na-" u="33">
      <f>τὰ</f>
      <e>ὁ</e>
    </t>
    <t p="9" n="8" a="[1]" o="a-p---na-" u="34">
      <f>θερινὰ</f>
    </t>
    <t p="9" n="9" a="[1]" o="n-p---na-" u="35">
      <f>ἔργα</f>
      <l r="n--p---na-">ἔργον</l>
      <e>ἔργον</e>
    </t>
    <t p="9" n="10" a="[2]" o="d--------" u="36">
      <f>καὶ</f>
      <l r="d---------">καί</l>
    </t>
    <t p="9" n="11" a="[1]" o="l-s---fa-" u="37">
      <f>τὴν</f>
    </t>
    <t p="10" n="1" a="[1]" o="a-s---fa-" u="38">
      <f>ἄλλην</f>
      <l r="a--s---fa-">ἄλλος</l>
      <e>ἄλλος</e>
    </t>
    <t p="10" n="2" a="[1]" o="n-s---fa-" u="39">
      <f>κατασπορὰν</f>
    </t>
    <t p="10" n="3" a="[1]" o="a-s---fa-" u="40">
      <f>πᾶσαν</f>
      <l r="a--s---fa-">πᾶς</l>
      <e>πᾶς</e>
    </t>
    <t p="10" n="4" a="[1]" o="r--------" u="41">
      <f>ἐν</f>
      <l r="r---------">ἐν</l>
      <e>εἰς</e>
      <e>ἐν</e>
    </t>
    <t p="10" n="5" a="[1]" o="n-s---fd-" u="42">
      <f>τούτωι</f>
    </t>
    <t p="10" n="6" a="[1]" o="v-pppemn-" u="43">
      <f>διαπορθμευόμενοι</f>
    </t>
    <t p="11" n="1" a="[1]" o="v1ppie---" u="44">
      <f>ποιούμεθα</f>
      <l r="v-1ppie---">ποιέω</l>
      <e>ποιέω</e>
    </t>
    <t p="11" n="2" a="[1]" join="b" o="u--------" u="45">
      <f>.</f>
    </t>
  </s>
</text>