<text text-id="p.cair.zen.4.59611">
  <sentence n="position in the document">
    <token p="passage-level id" n="position in @p" a="nth occurrence in @p" o="Mate tagger POS tag" u="position in s element" join="optional: join b(ack) or a(fter) for punctuation marks">
      <wordForm>word form of the token</wordForm>
      <lemma>
        <l1 r="POS tag as in PerseusUnderPhilologic">as many l1 elements as the lemmas found in PerseusUnderPhilologic for 
              the relevant word form AND morphological analysis</l1>
        <l2>as many l2 elements as the lemmas found in Morpheus for 
              the relevant word form AND morphological analysis</l2>
      </lemma>
    </token>
  </sentence>
  <s n="1">
    <t p="r.1" n="1" a="[1]" o="n-s---md-" u="1">
      <f>Ζήνωνι</f>
      <l>
        <l1 r="ne-s---md-">Ζήνων</l1>
      </l>
    </t>
    <t p="r.1" n="2" a="[1]" o="v-srppmv-" u="2">
      <f>χαί</f>
    </t>
    <t p="r.2" n="1" a="[1]" o="v--pna---" u="3">
      <f>ρειν</f>
    </t>
    <t p="r.2" n="2" a="[1]" join="b" o="u--------" u="4">
      <f>.</f>
    </t>
  </s>
  <s n="2">
    <t p="r.2" n="3" a="[1]" o="v1saim---" u="1">
      <f>ἐκομισάμην</f>
      <l>
        <l1 r="v-1saim---">κομίζω</l1>
        <l2>κομίζω</l2>
      </l>
    </t>
    <t p="r.2" n="4" a="[1]" o="r--------" u="2">
      <f>παρὰ</f>
      <l>
        <l1 r="r---------">παρά</l1>
      </l>
    </t>
    <t p="r.2" n="5" a="[1]" o="n-s---mg-" u="3">
      <f>Χεσερ</f>
    </t>
    <t p="r.3" n="1" a="[1]" o="a-s---mg-" u="4">
      <f>ταίου</f>
    </t>
    <t p="r.3" n="2" a="[1]" o="n-s---mg-" u="5">
      <f>ίτου</f>
    </t>
    <t p="r.3" n="3" a="[1]" o="a-s---mg-" u="6">
      <f>ἀργυρίου</f>
    </t>
    <t p="r.4" n="1" a="[1]" o="n-p---fa-" u="7">
      <f>δραχμὰς</f>
      <l>
        <l1 r="n--p---fa-">δραχμή</l1>
      </l>
    </t>
    <t p="r.4" n="2" a="[1]" o="c--------" u="8">
      <f>καὶ</f>
      <l>
        <l1 r="c---------">καί</l1>
        <l2>καί</l2>
      </l>
    </t>
    <t p="r.4" n="3" a="[1]" o="n-s---mg-" u="9">
      <f>χαλκοῦ</f>
      <l>
        <l1 r="n--s---mg-">χαλκός</l1>
        <l1 r="n--s---mg-">χαλκοῦς</l1>
        <l2>χαλκός</l2>
        <l2>χαλκοῦς</l2>
      </l>
    </t>
    <t p="r.4" n="4" a="[2]" o="n-p---fa-" u="10">
      <f>δραχμὰς</f>
      <l>
        <l1 r="n--p---fa-">δραχμή</l1>
      </l>
    </t>
    <t p="r.4" n="5" a="[1]" o="v3siia---" u="11">
      <f>ιε</f>
    </t>
    <t p="r.4" n="6" a="[1]" join="b" o="u--------" u="12">
      <f>.</f>
    </t>
  </s>
  <s n="3">
    <t p="r.4" n="7" a="[1]" o="--s---mg-" u="1">
      <f>γρά</f>
    </t>
    <t p="r.5" n="1" a="[1]" o="v2spia---" u="2">
      <f>φεις</f>
    </t>
    <t p="r.5" n="2" a="[1]" o="g--------" u="3">
      <f>δέ</f>
      <l>
        <l1 r="g---------">δέ</l1>
        <l2>δέ</l2>
      </l>
    </t>
    <t p="r.5" n="3" a="[1]" o="p-s---md-" u="4">
      <f>μοι</f>
    </t>
    <t p="r.5" n="4" a="[1]" o="r--------" u="5">
      <f>περὶ</f>
      <l>
        <l1 r="r---------">περί</l1>
      </l>
    </t>
    <t p="r.5" n="5" a="[1]" o="l-s---ng-" u="6">
      <f>τοῦ</f>
      <l>
        <l2>ὁ</l2>
      </l>
    </t>
    <t p="r.5" n="6" a="[1]" o="n-s---ng-" u="7">
      <f>κεράμου</f>
    </t>
    <t p="r.6" n="1" a="[1]" o="v-sapamn-" u="8">
      <f>σας</f>
    </t>
    <t p="r.6" n="2" a="[1]" o="d--------" u="9">
      <f>οὕτω</f>
      <l>
        <l1 r="dd--------">οὕτως</l1>
        <l2>οὕτως</l2>
      </l>
    </t>
    <t p="r.6" n="3" a="[1]" o="v2saim---" u="10">
      <f>χωνευ</f>
    </t>
    <t p="r.7" n="1" a="[1]" o="u--------" u="11">
      <f>ν</f>
    </t>
    <t p="r.7" n="2" a="[1]" o="d--------" u="12">
      <f>οὖν</f>
    </t>
    <t p="r.7" n="3" a="[1]" o="d--------" u="13">
      <f>οὕτως</f>
      <l>
        <l1 r="dd--------">οὕτως</l1>
        <l2>οὕτως</l2>
      </l>
    </t>
    <t p="r.7" n="4" a="[1]" join="b" o="u--------" u="14">
      <f>,</f>
    </t>
    <t p="r.7" n="5" a="[1]" o="a-p---nn-" u="15">
      <f>παρα</f>
    </t>
    <t p="r.8" n="1" a="[1]" o="v3sria---" u="16">
      <f>γέγονεν</f>
      <l>
        <l1 r="v-3sria---">γίγνομαι</l1>
        <l2>γίγνομαι</l2>
      </l>
    </t>
    <t p="r.8" n="2" a="[1]" o="g--------" u="17">
      <f>δέ</f>
      <l>
        <l1 r="g---------">δέ</l1>
        <l2>δέ</l2>
      </l>
    </t>
    <t p="r.8" n="3" a="[1]" o="p-s---md-" u="18">
      <f>μοι</f>
    </t>
    <t p="r.8" n="4" a="[1]" o="p-p---na-" u="19">
      <f>τὰ</f>
      <l>
        <l1 r="pa-p---na-">ὁ</l1>
        <l1 r="pr-p---na-">ὅς</l1>
      </l>
    </t>
    <t p="r.8" n="5" a="[1]" o="v2sasm---" u="20">
      <f>γράμ</f>
    </t>
    <t p="r.9" n="1" a="[1]" o="n-p---na-" u="21">
      <f>ματα</f>
    </t>
    <t p="r.9" n="2" a="[1]" o="n-s---fg-" u="22">
      <f>ὥρας</f>
      <l>
        <l1 r="n--s---fg-">ὥρα2</l1>
        <l2>ὥρα</l2>
      </l>
    </t>
    <t p="r.9" n="3" a="[1]" o="a-s---fg-" u="23">
      <f>ἑνδεκάτης</f>
      <l>
        <l1 r="a--s---fg-">ἑνδέκατος</l1>
        <l2>ἑνδέκατος</l2>
      </l>
    </t>
    <t p="r.10" n="1" a="[1]" o="d--------" u="24">
      <f>καὶ</f>
      <l>
        <l1 r="d---------">καί</l1>
      </l>
    </t>
    <t p="r.10" n="2" a="[1]" o="l-s---na-" u="25">
      <f>τὸ</f>
      <l>
        <l2>ὁ</l2>
      </l>
    </t>
    <t p="r.10" n="3" a="[1]" o="n-s---na-" u="26">
      <f>πλοῖον</f>
      <l>
        <l1 r="n--s---na-">πλοῖον</l1>
        <l2>πλοῖον</l2>
      </l>
    </t>
    <t p="r.10" n="4" a="[1]" o="d--------" u="27">
      <f>οὔπω</f>
      <l>
        <l1 r="d---------">οὔπω</l1>
        <l2>οὔπω</l2>
      </l>
    </t>
    <t p="r.10" n="5" a="[1]" o="v3saia---" u="28">
      <f>παρε</f>
    </t>
    <t p="r.11" n="1" a="[1]" o="v3slia---" u="29">
      <f>γεγόνει</f>
      <l>
        <l1 r="v-3slia---">γίγνομαι</l1>
        <l2>γίγνομαι</l2>
      </l>
    </t>
    <t p="r.11" n="2" a="[1]" join="b" o="u--------" u="30">
      <f>,</f>
    </t>
    <t p="r.11" n="3" a="[1]" o="c--------" u="31">
      <f>ὥστε</f>
      <l>
        <l1 r="c---------">ὥστε</l1>
      </l>
    </t>
    <t p="r.11" n="4" a="[1]" o="d--------" u="32">
      <f>κατʼ</f>
      <l>
        <l1 r="d---------">κατά</l1>
      </l>
    </t>
    <t p="r.11" n="5" a="[1]" o="p-s---ma-" u="33">
      <f>ἐμὲ</f>
    </t>
    <t p="r.12" n="1" a="[1]" o="p-s---na-" u="34">
      <f>οὐθὲν</f>
    </t>
    <t p="r.12" n="2" a="[1]" o="l-s---na-" u="35">
      <f>τὸ</f>
      <l>
        <l2>ὁ</l2>
      </l>
    </t>
    <t p="r.12" n="3" a="[1]" o="d--------" u="36">
      <f>κώλυμά</f>
    </t>
    <t p="r.12" n="4" a="[1]" o="v3spia---" u="37">
      <f>ἐστιν</f>
      <l>
        <l1 r="vc3spia---">εἰμί</l1>
        <l2>εἰμί</l2>
      </l>
    </t>
    <t p="r.12" n="5" a="[1]" join="b" o="u--------" u="38">
      <f>,</f>
    </t>
    <t p="r.12" n="6" a="[1]" o="d--------" u="39">
      <f>ἀλ</f>
    </t>
    <t p="r.13" n="1" a="[1]" o="d--------" u="40">
      <f>λʼ</f>
    </t>
    <t p="r.13" n="2" a="[1]" o="d--------" u="41">
      <f>ἢ</f>
      <l>
        <l1 r="d---------">τίη</l1>
      </l>
    </t>
    <t p="r.13" n="3" a="[1]" o="r--------" u="42">
      <f>ἐν</f>
      <l>
        <l1 r="r---------">ἐν</l1>
        <l2>εἰς</l2>
        <l2>ἐν</l2>
      </l>
    </t>
    <t p="r.13" n="4" a="[1]" o="l-p---md-" u="43">
      <f>τοῖς</f>
      <l>
        <l2>ὁ</l2>
      </l>
    </t>
    <t p="r.13" n="5" a="[1]" o="v3ppia---" u="44">
      <f>κατάγουσιν</f>
      <l>
        <l1 r="v-3ppia---">κατάγω</l1>
        <l2>κατάγω</l2>
      </l>
    </t>
    <t p="r.13" n="6" a="[1]" join="b" o="u--------" u="45">
      <f>.</f>
    </t>
  </s>
  <s n="4">
    <t p="r.13" n="7" a="[1]" o="l-p---nn-" u="1">
      <f>τὰ</f>
      <l>
        <l2>ὁ</l2>
      </l>
    </t>
    <t p="r.14" n="1" a="[1]" o="d--------" u="2">
      <f>μὲν</f>
    </t>
    <t p="r.14" n="2" a="[1]" o="d--------" u="3">
      <f>οὖν</f>
    </t>
    <t p="r.14" n="3" a="[1]" o="u--------" u="4">
      <f>σ</f>
    </t>
    <t p="r.14" n="4" a="[1]" o="d--------" u="5">
      <f>εὐθὺ</f>
      <l>
        <l1 r="d---------">εὐθύς</l1>
      </l>
    </t>
    <t p="r.14" n="5" a="[1]" o="v3sria---" u="6">
      <f>παραγε</f>
    </t>
    <t p="r.15" n="1" a="[1]" o="v-sppemn-" u="7">
      <f>νόμενος</f>
    </t>
    <t p="r.15" n="2" a="[1]" o="d--------" u="8">
      <f>τῆι</f>
      <l>
        <l1 r="d---------">τῇ</l1>
        <l2>τῇ</l2>
      </l>
    </t>
    <t p="r.15" n="3" a="[1]" o="d--------" u="9">
      <f>κα</f>
    </t>
    <t p="r.15" n="4" a="[1]" o="v2spme---" u="10">
      <f>ἐχώνευ</f>
    </t>
    <t p="r.16" n="1" a="[1]" o="v-sppafn-" u="11">
      <f>σα</f>
    </t>
    <t p="r.16" n="2" a="[1]" o="v-sppemn-" u="12">
      <f>προσδεχόμενος</f>
    </t>
    <t p="r.16" n="3" a="[1]" o="l-s---na-" u="13">
      <f>τὸ</f>
      <l>
        <l2>ὁ</l2>
      </l>
    </t>
    <t p="r.16" n="4" a="[1]" o="n-s---na-" u="14">
      <f>πλοῖ</f>
    </t>
    <t p="r.17" n="1" a="[1]" o="a-s---na-" u="15">
      <f>ον</f>
    </t>
    <t p="r.17" n="2" a="[1]" join="b" o="u--------" u="16">
      <f>,</f>
    </t>
    <t p="r.17" n="3" a="[1]" o="d--------" u="17">
      <f>καὶ</f>
      <l>
        <l1 r="d---------">καί</l1>
      </l>
    </t>
    <t p="r.17" n="4" a="[1]" o="l-p---na-" u="18">
      <f>τὰ</f>
      <l>
        <l2>ὁ</l2>
      </l>
    </t>
    <t p="r.17" n="5" a="[1]" o="a-p---na-" u="19">
      <f>λοιπὰ</f>
      <l>
        <l1 r="a--p---na-">λοιπός</l1>
      </l>
    </t>
    <t p="r.17" n="6" a="[1]" o="c--------" u="20">
      <f>δὲ</f>
    </t>
    <t p="r.17" n="7" a="[1]" o="a-p---na-" u="21">
      <f>ἕτοιμά</f>
      <l>
        <l1 r="a--p---na-">ἑτοῖμος</l1>
      </l>
    </t>
    <t p="r.18" n="1" a="[1]" o="v3spia---" u="22">
      <f>ἐστιν</f>
      <l>
        <l1 r="vc3spia---">εἰμί</l1>
        <l2>εἰμί</l2>
      </l>
    </t>
    <t p="r.18" n="2" a="[1]" join="b" o="u--------" u="23">
      <f>.</f>
    </t>
  </s>
  <s n="5">
    <t p="r.18" n="3" a="[1]" o="v2sama---" u="1">
      <f>γράψον</f>
      <l>
        <l1 r="v-2sama---">γράφω</l1>
        <l2>γράφω</l2>
      </l>
    </t>
    <t p="r.18" n="4" a="[1]" o="g--------" u="2">
      <f>δέ</f>
      <l>
        <l1 r="g---------">δέ</l1>
        <l2>δέ</l2>
      </l>
    </t>
    <t p="r.18" n="5" a="[1]" o="p-s---md-" u="3">
      <f>μοι</f>
    </t>
    <t p="r.18" n="6" a="[1]" o="c--------" u="4">
      <f>εἰ</f>
      <l>
        <l1 r="c---------">εἰ</l1>
        <l2>εἰ</l2>
      </l>
    </t>
    <t p="r.18" n="7" a="[1]" o="v2siie---" u="5">
      <f>πλεό</f>
    </t>
    <t p="r.19" n="1" a="[1]" o="v-sppamn-" u="6">
      <f>νων</f>
    </t>
    <t p="r.19" n="2" a="[1]" o="n-s---fa-" u="7">
      <f>χρείαν</f>
      <l>
        <l1 r="n--s---fa-">χρεία</l1>
        <l2>χρεία</l2>
      </l>
    </t>
    <t p="r.19" n="3" a="[1]" o="v2spia---" u="8">
      <f>ἔχεις</f>
      <l>
        <l1 r="v-2spia---">ἔχω</l1>
        <l2>ἔχω</l2>
      </l>
    </t>
    <t p="r.19" n="4" a="[1]" join="b" o="u--------" u="9">
      <f>·</f>
    </t>
  </s>
  <s n="6">
    <t p="r.19" n="5" a="[1]" o="v2spoe---" u="1">
      <f>προσαπο</f>
    </t>
    <t p="r.20" n="1" a="[1]" o="v1spie---" u="2">
      <f>βιῶμαι</f>
    </t>
    <t p="r.20" n="2" a="[1]" o="r--------" u="3">
      <f>πρὸ</f>
      <l>
        <l1 r="r---------">πρό</l1>
      </l>
    </t>
    <t p="r.20" n="3" a="[1]" o="l-s---ng-" u="4">
      <f>τοῦ</f>
      <l>
        <l2>ὁ</l2>
      </l>
    </t>
    <t p="r.20" n="4" a="[1]" o="a-p---ma-" u="5">
      <f>ἄλλους</f>
      <l>
        <l1 r="a--p---ma-">ἄλλος</l1>
        <l2>ἄλλος</l2>
      </l>
    </t>
    <t p="r.20" n="5" a="[1]" o="a-p---na-" u="6">
      <f>λα</f>
    </t>
    <t p="r.21" n="1" a="[1]" o="v--pna---" u="7">
      <f>βεῖν</f>
    </t>
    <t p="r.21" n="2" a="[1]" join="b" o="u--------" u="8">
      <f>.</f>
    </t>
  </s>
  <s n="7">
    <t p="r.21" n="3" a="[1]" o="v2spme---" u="1">
      <f>ἔρρωσο</f>
    </t>
    <t p="r.21" n="4" a="[2]" join="b" o="u--------" u="2">
      <f>.</f>
    </t>
  </s>
  <s n="8">
    <t p="r.21" n="5" a="[1]" o="n-s---md-" u="1">
      <f>Παῦνι</f>
    </t>
    <t p="r.21" n="6" a="[1]" o="-|-|-|-|-|-|-|-" u="2">
      <f>β</f>
    </t>
    <t p="r.21" n="7" a="[3]" join="b" o="u--------" u="3">
      <f>.</f>
    </t>
  </s>
  <s n="9">
    <t p="v.22" n="1" a="[1]" o="n-s---md-" u="1">
      <f>Παῦνι</f>
    </t>
    <t p="v.22" n="2" a="[1]" o="g--------" u="2">
      <f>γ</f>
    </t>
    <t p="v.22" n="3" a="[1]" join="b" o="u--------" u="3">
      <f>.</f>
    </t>
  </s>
</text>