<text text-id="p.oxy.41.2951">
  <sentence n="position in the document">
    <token p="passage-level id" n="position in @p" a="nth occurrence in @p" o="Mate tagger POS tag" u="position in s element" join="optional: join b(ack) or a(fter) for punctuation marks">
      <wordForm>word form of the token</wordForm>
      <lemma>
        <l1 r="POS tag as in PerseusUnderPhilologic">as many l1 elements as the lemmas found in PerseusUnderPhilologic for 
              the relevant word form AND morphological analysis</l1>
        <l2>as many l2 elements as the lemmas found in Morpheus for 
              the relevant word form AND morphological analysis</l2>
      </lemma>
    </token>
  </sentence>
  <s n="1">
    <t p="19" n="1" a="[1]" o="n-s---fg-" u="1">
      <f>Μαρίας</f>
      <l>
        <l1 r="ne-s---fg-">Μαρία</l1>
      </l>
    </t>
    <t p="19" n="2" a="[1]" o="n-s---fn-" u="2">
      <f>Βαρσίμις</f>
    </t>
    <t p="19" n="3" a="[1]" o="n-s---mg-" u="3">
      <f>Σαλαρᾶτος</f>
    </t>
    <t p="19" n="4" a="[1]" o="n-s---mg-" u="4">
      <f>ἀριθμοῦ</f>
      <l>
        <l1 r="n--s---mg-">ἀριθμός</l1>
        <l2>ἀριθμός</l2>
      </l>
    </t>
    <t p="19" n="5" a="[1]" o="v-sppamn-" u="5">
      <f>καταφράκτων</f>
    </t>
    <t p="19" n="6" a="[1]" join="b" o="u--------" u="6">
      <f>,</f>
    </t>
    <t p="19" n="7" a="[1]" o="r--------" u="7">
      <f>διʼ</f>
      <l>
        <l1 r="r---------">διά</l1>
      </l>
    </t>
    <t p="19" n="8" a="[1]" o="a-s---mg-" u="8">
      <f>ἐμοῦ</f>
      <l>
        <l2>ἐμός</l2>
      </l>
    </t>
    <t p="19" n="9" a="[1]" o="l-s---mg-" u="9">
      <f>τοῦ</f>
      <l>
        <l2>ὁ</l2>
      </l>
    </t>
    <t p="20" n="1" a="[1]" o="n-s---mg-" u="10">
      <f>πατρὸς</f>
      <l>
        <l1 r="n--s---mg-">πατήρ</l1>
      </l>
    </t>
    <t p="20" n="2" a="[1]" o="v-sppamg-" u="11">
      <f>κατέχοντος</f>
      <l>
        <l1 r="v--sppamg-">κατέχω</l1>
      </l>
    </t>
    <t p="20" n="3" a="[1]" o="p-s---ma-" u="12">
      <f>αὐτὸν</f>
      <l>
        <l1 r="pp-s---ma-">αὐτός</l1>
      </l>
    </t>
    <t p="20" n="4" a="[1]" o="r--------" u="13">
      <f>ὑπὸ</f>
      <l>
        <l1 r="r---------">ὑπό</l1>
        <l2>ὑπό</l2>
      </l>
    </t>
    <t p="20" n="5" a="[1]" o="l-s---fd-" u="14">
      <f>τῇ</f>
      <l>
        <l2>ὁ</l2>
      </l>
    </t>
    <t p="20" n="6" a="[1]" o="n-s---fd-" u="15">
      <f>χειρὶ</f>
      <l>
        <l1 r="n--s---fd-">χείρ</l1>
      </l>
    </t>
    <t p="20" n="7" a="[1]" o="r--------" u="16">
      <f>κατὰ</f>
      <l>
        <l1 r="r---------">κατά</l1>
        <l2>κατά</l2>
      </l>
    </t>
    <t p="20" n="8" a="[1]" o="l-p---ma-" u="17">
      <f>τοὺς</f>
    </t>
    <t p="20" n="9" a="[1]" o="n-p---mg-" u="18">
      <f>Ῥωμαίων</f>
    </t>
    <t p="20" n="10" a="[1]" o="n-p---ma-" u="19">
      <f>νόμους</f>
      <l>
        <l1 r="n--p---ma-">νόμος</l1>
        <l2>νόμος</l2>
        <l2>νομός</l2>
      </l>
    </t>
    <t p="20" n="11" a="[1]" join="b" o="u--------" u="20">
      <f>,</f>
    </t>
    <t p="21" n="1" a="[1]" o="n-p---mn-" u="21">
      <f>Βαρσίμιοσ</f>
    </t>
    <t p="21" n="2" a="[1]" o="n-s---mg-" u="22">
      <f>Βάσσου</f>
      <l>
        <l1 r="ne-s---mg-">Βάσσος</l1>
      </l>
    </t>
    <t p="21" n="3" a="[1]" o="a-s---fg-" u="23">
      <f>δεκαδάρχου</f>
    </t>
    <t p="21" n="4" a="[1]" o="n-s---fg-" u="24">
      <f>εἴλης</f>
    </t>
    <t p="21" n="5" a="[1]" o="l-s---fg-" u="25">
      <f>τῆς</f>
      <l>
        <l2>ὁ</l2>
      </l>
    </t>
    <t p="21" n="6" a="[1]" o="a-s---fg-" u="26">
      <f>αὐτῆς</f>
      <l>
        <l1 r="a--s---fg-">αὐτός</l1>
        <l2>αὐτός</l2>
      </l>
    </t>
    <t p="21" n="7" a="[1]" join="b" o="u--------" u="27">
      <f>,</f>
    </t>
    <t p="21" n="8" a="[1]" o="n-s---fa-" u="28">
      <f>πέπρακα</f>
    </t>
    <t p="21" n="9" a="[1]" o="d--------" u="29">
      <f>τῷ</f>
      <l>
        <l1 r="d---------">τῷ</l1>
        <l2>τῷ</l2>
        <l2>τῷ</l2>
      </l>
    </t>
    <t p="21" n="10" a="[1]" o="n-s---md-" u="30">
      <f>Αὐρηλίῳ</f>
    </t>
    <t p="22" n="1" a="[1]" o="a-s---md-" u="31">
      <f>Ἀπολλωνίῳ</f>
      <l>
        <l1 r="ae-s---md-">Ἀπολλώνιος</l1>
      </l>
    </t>
    <t p="22" n="2" a="[1]" o="n-s---md-" u="32">
      <f>ὀπτίωνι</f>
    </t>
    <t p="22" n="3" a="[1]" o="l-s---fa-" u="33">
      <f>τὴν</f>
    </t>
    <t p="22" n="4" a="[1]" o="n-s---fa-" u="34">
      <f>δούλην</f>
      <l>
        <l1 r="n--s---fa-">δούλη</l1>
        <l1 r="n--s---fa-">δοῦλος</l1>
        <l2>δοῦλος</l2>
      </l>
    </t>
    <t p="22" n="5" a="[1]" o="n-s---fa-" u="35">
      <f>Νίκην</f>
      <l>
        <l1 r="ne-s---fa-">νίκη</l1>
      </l>
    </t>
    <t p="22" n="6" a="[1]" o="v-sppefa-" u="36">
      <f>ἐπικεκλημένην</f>
    </t>
    <t p="23" n="1" a="[1]" o="d--------" u="37">
      <f>Μετεθεν</f>
    </t>
    <t p="23" n="2" a="[1]" join="b" o="u--------" u="38">
      <f>,</f>
    </t>
    <t p="23" n="3" a="[1]" o="n-s---nd-" u="39">
      <f>γένει</f>
      <l>
        <l1 r="n--s---nd-">γένος</l1>
        <l2>γένος</l2>
      </l>
    </t>
    <t p="23" n="4" a="[1]" o="n-s---fa-" u="40">
      <f>Ἀράβισσαν</f>
    </t>
    <t p="23" n="5" a="[2]" join="b" o="u--------" u="41">
      <f>,</f>
    </t>
    <t p="23" n="6" a="[1]" o="a-s---nd-" u="42">
      <f>ἁπλῷ</f>
      <l>
        <l1 r="a--s---nd-">ἁπλόος</l1>
        <l2>ἁπλόος</l2>
      </l>
    </t>
    <t p="23" n="7" a="[1]" o="n-s---nd-" u="43">
      <f>χρήματι</f>
      <l>
        <l1 r="n--s---nd-">χρῆμα</l1>
        <l2>χρῆμα</l2>
      </l>
    </t>
    <t p="23" n="8" a="[1]" o="d--------" u="44">
      <f>καὶ</f>
      <l>
        <l1 r="d---------">καί</l1>
      </l>
    </t>
    <t p="23" n="9" a="[1]" o="v-sppafa-" u="45">
      <f>οὖσαν</f>
      <l>
        <l1 r="vc-sppafa-">εἰμί</l1>
      </l>
    </t>
    <t p="23" n="10" a="[1]" o="d--------" u="46">
      <f>ἐκτὸς</f>
      <l>
        <l1 r="d---------">ἐκτός</l1>
      </l>
    </t>
    <t p="23" n="11" a="[1]" o="n-p---fn-" u="47">
      <f>ἱερᾶσ</f>
    </t>
    <t p="24" n="1" a="[1]" o="n-s---fg-" u="48">
      <f>νόσου</f>
      <l>
        <l1 r="n--s---fg-">νόσος</l1>
        <l2>νόσος</l2>
      </l>
    </t>
    <t p="24" n="2" a="[1]" o="d--------" u="49">
      <f>καὶ</f>
      <l>
        <l1 r="d---------">καί</l1>
      </l>
    </t>
    <t p="24" n="3" a="[1]" o="n-s---fg-" u="50">
      <f>ἐπαφῆς</f>
      <l>
        <l1 r="n--s---fg-">ἐπαφή</l1>
        <l2>ἐπαφή</l2>
      </l>
    </t>
    <t p="24" n="4" a="[1]" join="b" o="u--------" u="51">
      <f>,</f>
    </t>
    <t p="24" n="5" a="[1]" o="a-d---nn-" u="52">
      <f>τιμῆσ</f>
    </t>
    <t p="24" n="6" a="[1]" o="n-s---ng-" u="53">
      <f>ἀργυρίου</f>
      <l>
        <l1 r="n--s---ng-">ἀργύριον</l1>
        <l2>ἀργύριον</l2>
      </l>
    </t>
    <t p="24" n="7" a="[1]" o="a-p---ng-" u="54">
      <f>δηναρίων</f>
    </t>
    <t p="24" n="8" a="[1]" o="a-p---mg-" u="55">
      <f>δισχιλίων</f>
      <l>
        <l2>δισχίλιοι</l2>
      </l>
    </t>
    <t p="24" n="9" a="[1]" o="a-p---ng-" u="56">
      <f>διακοσίων</f>
      <l>
        <l2>διακόσιοι</l2>
      </l>
    </t>
    <t p="25" n="1" a="[1]" o="a--------" u="57">
      <f>πεντήκοντα</f>
    </t>
    <t p="25" n="2" a="[1]" o="a-p---ng-" u="58">
      <f>Πτολομαεικῶν</f>
    </t>
    <t p="25" n="3" a="[1]" o="c--------" u="59">
      <f>καὶ</f>
      <l>
        <l1 r="c---------">καί</l1>
        <l2>καί</l2>
      </l>
    </t>
    <t p="25" n="4" a="[1]" o="v3paia---" u="60">
      <f>ἀπέσχον</f>
      <l>
        <l1 r="v-3paia---">ἀπέχω</l1>
        <l2>ἀπέχω</l2>
      </l>
    </t>
    <t p="25" n="5" a="[1]" o="l-s---fa-" u="61">
      <f>τὴν</f>
    </t>
    <t p="25" n="6" a="[1]" o="n-s---fa-" u="62">
      <f>τιμὴν</f>
      <l>
        <l1 r="n--s---fa-">τιμή</l1>
      </l>
    </t>
    <t p="25" n="7" a="[1]" o="n-s---fd-" u="63">
      <f>παρʼ</f>
    </t>
    <t p="25" n="8" a="[1]" o="d--------" u="64">
      <f>αὐτοῦ</f>
      <l>
        <l1 r="dd--------">αὐτός</l1>
        <l2>αὐτοῦ</l2>
      </l>
    </t>
    <t p="26" n="1" a="[1]" o="d--------" u="65">
      <f>καὶ</f>
      <l>
        <l1 r="d---------">καί</l1>
      </l>
    </t>
    <t p="26" n="2" a="[1]" o="v1saia---" u="66">
      <f>ἀνέδωκα</f>
    </t>
    <t p="26" n="3" a="[1]" o="l-p---fa-" u="67">
      <f>τὰς</f>
    </t>
    <t p="26" n="4" a="[1]" o="v3sasp---" u="68">
      <f>ἀσφαλείασ</f>
    </t>
    <t p="26" n="5" a="[1]" join="b" o="u--------" u="69">
      <f>,</f>
    </t>
    <t p="26" n="6" a="[2]" o="d--------" u="70">
      <f>καὶ</f>
      <l>
        <l1 r="d---------">καί</l1>
      </l>
    </t>
    <t p="26" n="7" a="[1]" o="v-sapmmg-" u="71">
      <f>ἐπερωτηθεὶσ</f>
    </t>
    <t p="26" n="8" a="[1]" o="v1saia---" u="72">
      <f>ὡμολόγησα</f>
      <l>
        <l1 r="v-1saia---">ὁμολογέω</l1>
        <l2>ὁμολογέω</l2>
      </l>
    </t>
    <t p="26" n="9" a="[1]" o="c--------" u="73">
      <f>ὡς</f>
      <l>
        <l1 r="c---------">ὡς</l1>
        <l2>ὡς</l2>
      </l>
    </t>
    <t p="27" n="1" a="[1]" o="v3spie---" u="74">
      <f>πρόκιται</f>
    </t>
    <t p="27" n="2" a="[1]" join="b" o="u--------" u="75">
      <f>.</f>
    </t>
  </s>
  <s n="2">
    <t p="27" n="3" a="[1]" o="n-s---mn-" u="1">
      <f>Ῥοῦφος</f>
      <l>
        <l1 r="ne-s---mn-">Ῥοῦφος</l1>
      </l>
    </t>
    <t p="27" n="4" a="[1]" o="d--------" u="2">
      <f>Ἀβεδσάι</f>
    </t>
    <t p="27" n="5" a="[1]" o="v-sppamn-" u="3">
      <f>ὀπτίων</f>
    </t>
    <t p="27" n="6" a="[1]" o="n-s---mg-" u="4">
      <f>ἀριθμοῦ</f>
      <l>
        <l1 r="n--s---mg-">ἀριθμός</l1>
        <l2>ἀριθμός</l2>
      </l>
    </t>
    <t p="27" n="7" a="[1]" o="l-p---mg-" u="5">
      <f>τῶν</f>
      <l>
        <l2>ὁ</l2>
      </l>
    </t>
    <t p="27" n="8" a="[1]" o="n-p---mg-" u="6">
      <f>Σαλαράτων</f>
    </t>
    <t p="27" n="9" a="[1]" o="v-sppamn-" u="7">
      <f>περεγρίνων</f>
    </t>
    <t p="28" n="1" a="[1]" o="v1saia---" u="8">
      <f>ἔγραψα</f>
      <l>
        <l1 r="v-1saia---">γράφω</l1>
        <l2>γράφω</l2>
      </l>
    </t>
    <t p="28" n="2" a="[1]" o="r--------" u="9">
      <f>ὑπὲρ</f>
      <l>
        <l1 r="r---------">ὑπέρ</l1>
      </l>
    </t>
    <t p="28" n="3" a="[1]" o="d--------" u="10">
      <f>αὐτοῦ</f>
      <l>
        <l1 r="dd--------">αὐτός</l1>
        <l2>αὐτοῦ</l2>
      </l>
    </t>
    <t p="28" n="4" a="[1]" o="n-p---na-" u="11">
      <f>γράμματα</f>
      <l>
        <l1 r="n--p---na-">γράμμα</l1>
        <l2>γράμμα</l2>
      </l>
    </t>
    <t p="28" n="5" a="[1]" o="d--------" u="12">
      <f>μὴ</f>
      <l>
        <l1 r="d---------">μή</l1>
      </l>
    </t>
    <t p="28" n="6" a="[1]" o="v3sama---" u="13">
      <f>εἰδότοσ</f>
    </t>
    <t p="28" n="7" a="[1]" join="b" o="u--------" u="14">
      <f>,</f>
    </t>
    <t p="28" n="8" a="[1]" o="l-s---fg-" u="15">
      <f>τῆς</f>
      <l>
        <l2>ὁ</l2>
      </l>
    </t>
    <t p="28" n="9" a="[1]" o="n-s---fg-" u="16">
      <f>χειρὸσ</f>
    </t>
    <t p="28" n="10" a="[2]" o="d--------" u="17">
      <f>αὐτοῦ</f>
      <l>
        <l1 r="dd--------">αὐτός</l1>
        <l2>αὐτοῦ</l2>
      </l>
    </t>
    <t p="29" n="1" a="[1]" o="v-sppefg-" u="18">
      <f>κατεχομένης</f>
      <l>
        <l1 r="v--sppefg-">κατέχω</l1>
      </l>
    </t>
    <t p="29" n="2" a="[1]" join="b" o="u--------" u="19">
      <f>,</f>
    </t>
    <t p="29" n="3" a="[1]" o="c--------" u="20">
      <f>καὶ</f>
      <l>
        <l1 r="c---------">καί</l1>
        <l2>καί</l2>
      </l>
    </t>
    <t p="29" n="4" a="[1]" o="p1s---mn-" u="21">
      <f>βεβαιῶ</f>
    </t>
    <t p="29" n="5" a="[1]" o="l-s---fa-" u="22">
      <f>τὴν</f>
    </t>
    <t p="29" n="6" a="[1]" o="n-s---fa-" u="23">
      <f>δούλην</f>
      <l>
        <l1 r="n--s---fa-">δούλη</l1>
        <l1 r="n--s---fa-">δοῦλος</l1>
        <l2>δοῦλος</l2>
      </l>
    </t>
    <t p="29" n="7" a="[1]" o="n-s---fa-" u="24">
      <f>Νίκην</f>
      <l>
        <l1 r="ne-s---fa-">νίκη</l1>
      </l>
    </t>
    <t p="29" n="8" a="[1]" o="v-sppefa-" u="25">
      <f>ἐπικεκλημένην</f>
    </t>
    <t p="30" n="1" a="[1]" o="n-s---fa-" u="26">
      <f>Σαπρίκιν</f>
    </t>
    <t p="30" n="2" a="[1]" join="b" o="u--------" u="27">
      <f>,</f>
    </t>
    <t p="30" n="3" a="[1]" o="d--------" u="28">
      <f>καὶ</f>
      <l>
        <l1 r="d---------">καί</l1>
      </l>
    </t>
    <t p="30" n="4" a="[1]" o="v3siia---" u="29">
      <f>ἐπερωτηθεὶσ</f>
    </t>
    <t p="30" n="5" a="[1]" o="v1saia---" u="30">
      <f>ὡμολόγησα</f>
      <l>
        <l1 r="v-1saia---">ὁμολογέω</l1>
        <l2>ὁμολογέω</l2>
      </l>
    </t>
    <t p="30" n="6" a="[1]" o="c--------" u="31">
      <f>ὡς</f>
      <l>
        <l1 r="c---------">ὡς</l1>
        <l2>ὡς</l2>
      </l>
    </t>
    <t p="30" n="7" a="[1]" o="v3spie---" u="32">
      <f>πρόκειται</f>
      <l>
        <l2>πρόκειμαι</l2>
      </l>
    </t>
    <t p="30" n="8" a="[1]" join="b" o="u--------" u="33">
      <f>.</f>
    </t>
  </s>
  <s n="3">
    <t p="31" n="1" a="[1]" o="n-s---fn-" u="1">
      <f>Βαρσίμις</f>
    </t>
    <t p="31" n="2" a="[1]" o="n-s---mn-" u="2">
      <f>Βάσσος</f>
      <l>
        <l1 r="ne-s---mn-">Βάσσος</l1>
      </l>
    </t>
    <t p="31" n="3" a="[1]" o="n-s---mn-" u="3">
      <f>δεκάδαρχος</f>
    </t>
    <t p="31" n="4" a="[1]" o="v1sria---" u="4">
      <f>πέπρακα</f>
    </t>
    <t p="31" n="5" a="[1]" o="c--------" u="5">
      <f>καὶ</f>
      <l>
        <l1 r="c---------">καί</l1>
        <l2>καί</l2>
      </l>
    </t>
    <t p="31" n="6" a="[1]" o="v3paia---" u="6">
      <f>ἀπέσχον</f>
      <l>
        <l1 r="v-3paia---">ἀπέχω</l1>
        <l2>ἀπέχω</l2>
      </l>
    </t>
    <t p="31" n="7" a="[1]" o="l-s---fa-" u="7">
      <f>τὴν</f>
    </t>
    <t p="31" n="8" a="[1]" o="n-s---fa-" u="8">
      <f>τιμὴν</f>
      <l>
        <l1 r="n--s---fa-">τιμή</l1>
      </l>
    </t>
    <t p="31" n="9" a="[2]" o="d--------" u="9">
      <f>καὶ</f>
      <l>
        <l1 r="d---------">καί</l1>
      </l>
    </t>
    <t p="31" n="10" a="[1]" o="v3saip---" u="10">
      <f>ὡμολόγη</f>
    </t>
    <t p="32" n="1" a="[1]" o="v-sppafn-" u="11">
      <f>σα</f>
    </t>
    <t p="32" n="2" a="[1]" o="c--------" u="12">
      <f>ὡς</f>
      <l>
        <l1 r="c---------">ὡς</l1>
        <l2>ὡς</l2>
      </l>
    </t>
    <t p="32" n="3" a="[1]" o="v3spie---" u="13">
      <f>πρόκειται</f>
      <l>
        <l2>πρόκειμαι</l2>
      </l>
    </t>
    <t p="32" n="4" a="[1]" join="b" o="u--------" u="14">
      <f>.</f>
    </t>
  </s>
</text>